pypiplot/__init__.py
pypiplot/examples.py
pypiplot/pypiplot.py
pypiplot/data/__init__.py
pypiplot-2.0.1.dist-info/LICENSE
pypiplot-2.0.1.dist-info/METADATA
pypiplot-2.0.1.dist-info/WHEEL
pypiplot-2.0.1.dist-info/top_level.txt
pypiplot-2.0.1.dist-info/RECORD
