Metadata-Version: 2.1
Name: pypiplot
Version: 2.0.1
Summary: Python package to count and plot the number of downloads from Pypi.
Home-page: https://erdogant.github.io/pypiplot
Download-URL: https://github.com/erdogant/pypiplot/archive/2.0.1.tar.gz
Author: Erdogan Taskesen
Author-email: erdogant@gmail.com
License: UNKNOWN
Platform: UNKNOWN
Classifier: Programming Language :: Python :: 3
Classifier: License :: OSI Approved :: MIT License
Classifier: Operating System :: OS Independent
Requires-Python: >=3
License-File: LICENSE
Requires-Dist: matplotlib
Requires-Dist: numpy
Requires-Dist: pandas
Requires-Dist: pypistats
Requires-Dist: d3heatmap
Requires-Dist: fsspec
Requires-Dist: calplot
